asp2cnl/__init__.py
asp2cnl/asp2cnl.py
asp2cnl/compiler.py
asp2cnl/parser.py
asp2cnl/asp_core_2_grammar/asp_grammar.lark
asp2nl/__init__.py
asp2nl/asp2nl.py
cnl2nl/__init__.py
cnl2nl/cnl2nl.py
asp2cnl-1.0.1.dist-info/LICENSE
asp2cnl-1.0.1.dist-info/METADATA
asp2cnl-1.0.1.dist-info/WHEEL
asp2cnl-1.0.1.dist-info/entry_points.txt
asp2cnl-1.0.1.dist-info/top_level.txt
asp2cnl-1.0.1.dist-info/RECORD
