Metadata-Version: 2.1
Name: asp2cnl
Version: 1.0.1
Summary: A tool for converting Answer Set Programming into a Controlled Natural Language based on English
Home-page: https://github.com/dodaro/asp2cnl
Author: Carmine Dodaro
Author-email: carmine.dodaro@unical.it
Maintainer: Kristian Reale
Maintainer-email: kristian.reale@unical.it
License: Apache License
Requires-Python: >=3.10
License-File: LICENSE
Requires-Dist: lark
Requires-Dist: inflect
Requires-Dist: multipledispatch
Requires-Dist: cnl2asp
